[
   {
      "deadline": "02/01/26",
      "hasNotResponded": [],
      "hasResponded": [
         "james",
         "srinath",
         "barb",
         "adriana",
         "david_l"
      ],
      "name": "BVC faculty monthly coffee chat",
      "numViableMeetingTimesSoFar": 0,
      "when2meet": "https://when2meet.com/?34658992-xP2rP"
   },
   {
      "deadline": "02/01/26",
      "hasNotResponded": [],
      "hasResponded": [
         "lana",
         "arman",
         "arin"
      ],
      "name": "CS 2240 staff meeting",
      "numViableMeetingTimesSoFar": 9,
      "when2meet": "https://when2meet.com/?34658993-5rR7L"
   },
   {
      "deadline": "02/01/26",
      "hasNotResponded": [],
      "hasResponded": [
         "faisal",
         "autumn"
      ],
      "name": "CS 1950U staff meeting",
      "numViableMeetingTimesSoFar": 18,
      "when2meet": "https://when2meet.com/?34658994-ljfK2"
   },
   {
      "deadline": "02/01/26",
      "hasNotResponded": [],
      "hasResponded": [
         "adriana",
         "will",
         "karima"
      ],
      "name": "surfacing abstractions",
      "numViableMeetingTimesSoFar": 2,
      "when2meet": "https://when2meet.com/?34658995-PM1zn"
   },
   {
      "deadline": "02/01/26",
      "hasNotResponded": [
         "henry_meta"
      ],
      "hasResponded": [
         "aditya",
         "henry"
      ],
      "name": "Part-level affordances weekly",
      "numViableMeetingTimesSoFar": 6,
      "when2meet": "https://when2meet.com/?34658996-bgREF"
   },
   {
      "deadline": "02/01/26",
      "hasNotResponded": [
         "matheus",
         "thibault",
         "sid",
         "yifan_w"
      ],
      "hasResponded": [
         "pranav",
         "aditya",
         "zhiqin"
      ],
      "name": "Aditya SuperFit Project Meeting",
      "numViableMeetingTimesSoFar": 11,
      "when2meet": "https://when2meet.com/?34658997-c6t1U"
   },
   {
      "deadline": "02/01/26",
      "hasNotResponded": [
         "noam"
      ],
      "hasResponded": [
         "arman",
         "tianshu"
      ],
      "name": "JacobianGen Project Meeting",
      "numViableMeetingTimesSoFar": 43,
      "when2meet": "https://when2meet.com/?34658998-zI7tA"
   },
   {
      "deadline": "02/01/26",
      "hasNotResponded": [
         "derek",
         "maxim",
         "victor"
      ],
      "hasResponded": [],
      "name": "Maxim + Roblox",
      "numViableMeetingTimesSoFar": 0,
      "when2meet": "https://when2meet.com/?34658999-UdTWh"
   },
   {
      "deadline": "02/01/26",
      "hasNotResponded": [
         "stewart"
      ],
      "hasResponded": [],
      "name": "Zero-shot object orientation",
      "numViableMeetingTimesSoFar": 0,
      "when2meet": "https://when2meet.com/?34659000-aWVNO"
   },
   {
      "deadline": "02/01/26",
      "hasNotResponded": [
         "sid"
      ],
      "hasResponded": [
         "marzia",
         "henro",
         "adrien"
      ],
      "name": "Henro SDF Program Inference Project",
      "numViableMeetingTimesSoFar": 9,
      "when2meet": "https://when2meet.com/?34659002-eB9iI"
   },
   {
      "deadline": "02/01/26",
      "hasNotResponded": [
         "aruna"
      ],
      "hasResponded": [
         "arman",
         "nicole_g"
      ],
      "name": "Monte Carlo DTN",
      "numViableMeetingTimesSoFar": 7,
      "when2meet": "https://when2meet.com/?34659003-MhG2Q"
   },
   {
      "deadline": "02/01/26",
      "hasNotResponded": [],
      "hasResponded": [
         "adriana",
         "karima",
         "jason_l"
      ],
      "name": "Jason Project Meeting",
      "numViableMeetingTimesSoFar": 5,
      "when2meet": "https://when2meet.com/?34659005-WucVs"
   },
   {
      "deadline": "02/01/26",
      "hasNotResponded": [
         "paul_g",
         "rana"
      ],
      "hasResponded": [
         "ben_a"
      ],
      "name": "Ben Project Meeting",
      "numViableMeetingTimesSoFar": 20,
      "when2meet": "https://when2meet.com/?34659006-WEAKq"
   },
   {
      "deadline": "02/01/26",
      "hasNotResponded": [
         "kenny",
         "paul_g"
      ],
      "hasResponded": [
         "jeffrey",
         "ben_a",
         "yuqiao"
      ],
      "name": "Neurosymbolic 3D models",
      "numViableMeetingTimesSoFar": 2,
      "when2meet": "https://when2meet.com/?34659007-c8mgN"
   },
   {
      "deadline": "02/01/26",
      "hasNotResponded": [],
      "hasResponded": [
         "adriana",
         "aditya",
         "milin"
      ],
      "name": "Neurocad",
      "numViableMeetingTimesSoFar": 8,
      "when2meet": "https://when2meet.com/?34659008-RMsN3"
   },
   {
      "deadline": "02/01/26",
      "hasNotResponded": [
         "chengye"
      ],
      "hasResponded": [
         "marzia",
         "adrien",
         "xiaoxi",
         "yuanbo"
      ],
      "name": "Sketch2CAD Projects Meeting",
      "numViableMeetingTimesSoFar": 3,
      "when2meet": "https://when2meet.com/?34659009-mFM7Y"
   },
   {
      "deadline": "02/01/26",
      "hasNotResponded": [
         "maxim",
         "chengye",
         "tanish",
         "chujun"
      ],
      "hasResponded": [
         "ben_a",
         "aditya",
         "una",
         "yuanbo",
         "pranav",
         "xiaoxi",
         "jason_l",
         "ryan_l",
         "yubo",
         "arman",
         "henry",
         "lyfey",
         "yuqiao"
      ],
      "name": "Daniel's Group Meeting",
      "numViableMeetingTimesSoFar": 2,
      "when2meet": "https://when2meet.com/?34659010-w9W2W"
   }
]