[
   {
      "deadline": "06/21/25",
      "hasNotResponded": [],
      "hasResponded": [
         "victor",
         "derek",
         "maxim"
      ],
      "name": "Maxim + Roblox",
      "numViableMeetingTimesSoFar": 5,
      "when2meet": "https://when2meet.com/?31009750-DPUod"
   },
   {
      "deadline": "06/21/25",
      "hasNotResponded": [],
      "hasResponded": [
         "kenny",
         "jean"
      ],
      "name": "NGSP",
      "numViableMeetingTimesSoFar": 13,
      "when2meet": "https://when2meet.com/?31009751-wGIjL"
   },
   {
      "deadline": "06/21/25",
      "hasNotResponded": [],
      "hasResponded": [
         "stewart",
         "nirayka"
      ],
      "name": "Zero-shot object orientation",
      "numViableMeetingTimesSoFar": 6,
      "when2meet": "https://when2meet.com/?31009752-hbVSa"
   },
   {
      "deadline": "06/21/25",
      "hasNotResponded": [],
      "hasResponded": [
         "xiaoyan",
         "zekun",
         "srinath",
         "rahul"
      ],
      "name": "Human-Scene Interaction",
      "numViableMeetingTimesSoFar": 1,
      "when2meet": "https://when2meet.com/?31009753-ZtIUe"
   },
   {
      "deadline": "06/21/25",
      "hasNotResponded": [],
      "hasResponded": [
         "henro",
         "marzia",
         "adrien",
         "sid"
      ],
      "name": "Henro SDF Program Inference Project",
      "numViableMeetingTimesSoFar": 1,
      "when2meet": "https://when2meet.com/?31009754-ZKNW2"
   },
   {
      "deadline": "06/21/25",
      "hasNotResponded": [],
      "hasResponded": [
         "arman",
         "karina",
         "stephen_c",
         "yeganeh"
      ],
      "name": "Study group leader checkin",
      "numViableMeetingTimesSoFar": 10,
      "when2meet": "https://when2meet.com/?31009755-XAtHO"
   },
   {
      "deadline": "06/21/25",
      "hasNotResponded": [],
      "hasResponded": [
         "arman",
         "nicole_g",
         "aruna"
      ],
      "name": "Harmonic measure features",
      "numViableMeetingTimesSoFar": 45,
      "when2meet": "https://when2meet.com/?31009756-QHl8l"
   },
   {
      "deadline": "06/21/25",
      "hasNotResponded": [],
      "hasResponded": [
         "arman"
      ],
      "name": "Arman + Daniel",
      "numViableMeetingTimesSoFar": 55,
      "when2meet": "https://when2meet.com/?31009757-Ehcq2"
   },
   {
      "deadline": "06/21/25",
      "hasNotResponded": [],
      "hasResponded": [
         "bilal",
         "yuanbo",
         "chengye"
      ],
      "name": "Sketch-to-CAD spin-offs",
      "numViableMeetingTimesSoFar": 17,
      "when2meet": "https://when2meet.com/?31009758-sgV5c"
   },
   {
      "deadline": "06/21/25",
      "hasNotResponded": [],
      "hasResponded": [
         "jason_l",
         "adriana"
      ],
      "name": "Jason project brainstorming",
      "numViableMeetingTimesSoFar": 9,
      "when2meet": "https://when2meet.com/?31009759-84JaK"
   },
   {
      "deadline": "06/21/25",
      "hasNotResponded": [],
      "hasResponded": [
         "ben_a"
      ],
      "name": "Ben project brainstorming",
      "numViableMeetingTimesSoFar": 39,
      "when2meet": "https://when2meet.com/?31009760-AO8Ff"
   },
   {
      "deadline": "06/21/25",
      "hasNotResponded": [
         "niloy"
      ],
      "hasResponded": [
         "paul_g",
         "kenny",
         "yuqiao",
         "pranav",
         "tj"
      ],
      "name": "Neurosymbolic 3D models",
      "numViableMeetingTimesSoFar": 3,
      "when2meet": "https://when2meet.com/?31009761-359r9"
   },
   {
      "deadline": "06/21/25",
      "hasNotResponded": [],
      "hasResponded": [
         "nicole_g",
         "aruna"
      ],
      "name": "Aruna & Nicole checkin",
      "numViableMeetingTimesSoFar": 54,
      "when2meet": "https://when2meet.com/?31009762-hEK3I"
   },
   {
      "deadline": "06/21/25",
      "hasNotResponded": [],
      "hasResponded": [
         "faisal",
         "apoorva",
         "spandan",
         "gavin"
      ],
      "name": "CS 1230 course dev checkin",
      "numViableMeetingTimesSoFar": 4,
      "when2meet": "https://when2meet.com/?31009763-rTvD3"
   },
   {
      "deadline": "06/21/25",
      "hasNotResponded": [],
      "hasResponded": [
         "milin",
         "adriana"
      ],
      "name": "Neurocad",
      "numViableMeetingTimesSoFar": 3,
      "when2meet": "https://when2meet.com/?31009764-Iz6AZ"
   },
   {
      "deadline": "06/21/25",
      "hasNotResponded": [],
      "hasResponded": [
         "adrien",
         "xiaoxi",
         "yuanbo"
      ],
      "name": "Improved sketch lifting",
      "numViableMeetingTimesSoFar": 0,
      "when2meet": "https://www.when2meet.com/?31037257-vrAWI"
   }
]